microprojects/__init__.py
microprojects/__main__.py
microprojects/calc/.gitignore
microprojects/calc/README.md
microprojects/calc/__init__.py
microprojects/calc/__main__.py
microprojects/calc/analyzer.py
microprojects/calc/calculator.py
microprojects/calc/requirements.txt
microprojects/calc/tests/__init__.py
microprojects/calc/tests/check50/.cs50.yml
microprojects/calc/tests/check50/__init__.py
microprojects/calc/tests/pytest/__init__.py
microprojects/calc/tests/pytest/test_examples.py
microprojects/calc/tests/pytest/test_fishchecks.py
microprojects/ngit/.gitignore
microprojects/ngit/README.md
microprojects/ngit/__init__.py
microprojects/ngit/__main__.py
microprojects/ngit/libngit.py
microprojects/ngit/log.py
microprojects/ngit/ngit_utils.py
microprojects/ngit/object.py
microprojects/ngit/object_utils.py
microprojects/ngit/repository.py
microprojects/ngit/requirements.txt
microprojects/ngit/tests/check50/.cs50.yml
microprojects/ngit/tests/check50/__init__.py
microprojects/ngit/tests/pytests/__init__.py
microprojects-0.1.1.dist-info/METADATA
microprojects-0.1.1.dist-info/WHEEL
microprojects-0.1.1.dist-info/entry_points.txt
microprojects-0.1.1.dist-info/licenses/LICENSE
microprojects-0.1.1.dist-info/RECORD
